{
  "accounts": [
    {
      "id": "1",
      "username": "admin",
      "email": "admin@handbag.com",
      "password": "Admin123!",
      "fullName": "Administrator",
      "secretQuestion": "What is your favorite color?",
      "secretAnswer": "Blue"
    },
    {
      "id": 1756139351977,
      "username": "kim anh",
      "email": "kimanh@gmail.com",
      "password": "33204K@nh",
      "fullName": "kim anh",
      "secretQuestion": "What is the name of your first pet?",
      "secretAnswer": "ky"
    }
  ]
}